gpttui/__init__.py
gpttui/database/__init__.py
gpttui/database/base.py
gpttui/database/sqlite.py
gpttui/models/__init__.py
gpttui/models/base.py
gpttui/models/chatsonic.py
gpttui/models/colossal.py
gpttui/models/openai.py
gpttui/tui/__init__.py
gpttui/tui/app.py
gpttui/tui/config.py
gpttui/tui/front.py
gpttui/tui/init.py
gpttui/tui/main.py
gpttui-0.6.0.dist-info/entry_points.txt
gpttui-0.6.0.dist-info/WHEEL
gpttui-0.6.0.dist-info/METADATA
gpttui-0.6.0.dist-info/RECORD
