Metadata-Version: 2.1
Name: gpttui
Version: 0.6.0
Summary: TUI to interact with gpt models.
Author-email: Juan Lara <julara@unal.edu.co>
Requires-Python: >3.8
Requires-Dist: textual[dev]
Requires-Dist: pydantic
Requires-Dist: pyperclip
Requires-Dist: openai
Requires-Dist: httpx
Requires-Dist: click
Requires-Dist: pynvim ; extra == "dev"
Requires-Dist: flit ; extra == "dev"
Requires-Dist: pytest ; extra == "dev"
Requires-Dist: black ; extra == "dev"
Provides-Extra: dev
